oscer/__init__.py
oscer-0.1.data/scripts/oscer
oscer-0.1.dist-info/LICENSE
oscer-0.1.dist-info/METADATA
oscer-0.1.dist-info/WHEEL
oscer-0.1.dist-info/top_level.txt
oscer-0.1.dist-info/RECORD
