Metadata-Version: 2.1
Name: oscer
Version: 0.1
Summary: A very simple command line OpenSoundControl sender
Home-page: https://github.com/bgola/oscer
Author: Bruno Gola
Author-email: me@bgo.la
License: UNKNOWN
Keywords: udp osc opensoundcontrol
Platform: UNKNOWN
Classifier: Programming Language :: Python :: 3
Classifier: License :: OSI Approved :: GNU General Public License v3 or later (GPLv3+)
Classifier: Operating System :: OS Independent
Requires-Python: >=3.7
Requires-Dist: python-osc (==1.7.4)
